LICENSE
README.md
setup.py
WebifyPy/__init__.py
WebifyPy/components.py
WebifyPy/forms.py
WebifyPy/js_components.py
WebifyPy/pre_components.py
WebifyPy/styled_components.py
WebifyPy/styling.py
WebifyPy.egg-info/PKG-INFO
WebifyPy.egg-info/SOURCES.txt
WebifyPy.egg-info/dependency_links.txt
WebifyPy.egg-info/top_level.txt