Metadata-Version: 2.1
Name: WebifyPy
Version: 0.3.0
Summary: A Python package for web development
Home-page: https://github.com/ishanoshada/WebifyPy
Author: Ishan Oshada
Author-email: ic31908@gmail.com
License: MIT
Project-URL: Bug Reports, https://github.com/ishanoshada/WebifyPy/issues
Project-URL: Source, https://github.com/ishan oshada/WebifyPy
Keywords: web development,Python package
Platform: UNKNOWN
Classifier: Development Status :: 3 - Alpha
Classifier: Intended Audience :: Developers
Classifier: License :: OSI Approved :: MIT License
Classifier: Programming Language :: Python :: 3
Classifier: Programming Language :: Python :: 3.6
Classifier: Programming Language :: Python :: 3.7
Classifier: Programming Language :: Python :: 3.8
Classifier: Programming Language :: Python :: 3.9
Classifier: Programming Language :: Python :: 3.10
Classifier: Operating System :: OS Independent
